aacommons/__init__.py
aacommons/contentprovider/ContentProvider.py
aacommons/contentprovider/RedisStore.py
aacommons/contentprovider/__init__.py
aacommons/contentprovider/util.py
aacommons/dataparser/AirRecorder.py
aacommons/dataparser/__init__.py
aacommons/dataparser/cli/AbstractTableParser.py
aacommons/dataparser/cli/CliParser.py
aacommons/dataparser/cli/CliParserBase.py
aacommons/dataparser/cli/GenericJsonCsvTableParser.py
aacommons/dataparser/cli/GenericRegexTableParser.py
aacommons/dataparser/cli/RowColumnTableParser.py
aacommons/dataparser/cli/RowColumnTableParserAcxStd.py
aacommons/dataparser/cli/RowColumnTableParserAosDpStd.py
aacommons/dataparser/cli/RowColumnTableParserAosSmart.py
aacommons/dataparser/cli/RowColumnTableParserAosStd.py
aacommons/dataparser/cli/TableHelpers.py
aacommons/dataparser/cli/__init__.py
aacommons/dataparser/cli/arcli/ArCliContentProvider.py
aacommons/dataparser/cli/arcli/ArCliContext.py
aacommons/dataparser/cli/arcli/ArCliDocuments.py
aacommons/dataparser/cli/arcli/ArCliParser.py
aacommons/dataparser/cli/arcli/ArCliParserRequest.py
aacommons/dataparser/cli/arcli/ArCliResult.py
aacommons/dataparser/cli/arcli/ArCliSampleRunner.py
aacommons/dataparser/cli/arcli/__init__.py
aacommons/helpers/__init__.py
aacommons/helpers/get_my_ip.py
aacommons/helpers/jstyleson_lint.py
aacommons/misc/Stats.py
aacommons/misc/__init__.py
aacommons-0.2.9.dist-info/licenses/LICENSE
aacommons-0.2.9.dist-info/licenses/NOTICE
aacommons-0.2.9.dist-info/METADATA
aacommons-0.2.9.dist-info/WHEEL
aacommons-0.2.9.dist-info/top_level.txt
aacommons-0.2.9.dist-info/RECORD
