Metadata-Version: 2.4
Name: aacommons
Version: 0.2.9
Summary: aacommons
Home-page: 
Author: Thomas Bastian, Jeffrey Goff, Albert Pang
License-File: LICENSE
License-File: NOTICE
Requires-Dist: hiredis
Requires-Dist: jstyleson
Requires-Dist: munch
Requires-Dist: PyYAML
Requires-Dist: redis
Requires-Dist: requests
Requires-Dist: urllib3
Dynamic: author
Dynamic: description
Dynamic: description-content-type
Dynamic: license-file
Dynamic: requires-dist
Dynamic: summary
